{
  "project_info": {
    "project_number": "1093191311629",
    "project_id": "aplay-b7c41",
    "storage_bucket": "aplay-b7c41.firebasestorage.app"
  },
  "client": [
    {
      "client_info": {
        "mobilesdk_app_id": "1:1093191311629:android:b827e6839217a03aecd044",
        "android_client_info": {
          "package_name": "com.aplay.a_play"
        }
      },
      "oauth_client": [],
      "api_key": [
        {
          "current_key": "AIzaSyAuSQPdsayTWgRrjq6CutNE0_e4UIqirt8"
        }
      ],
      "services": {
        "appinvite_service": {
          "other_platform_oauth_client": []
        }
      }
    }
  ],
  "configuration_version": "1"
}